climate_indices/__init__.py
climate_indices/__main__.py
climate_indices/__spi__.py
climate_indices/compute.py
climate_indices/eto.py
climate_indices/indices.py
climate_indices/lmoments.py
climate_indices/palmer.py
climate_indices/utils.py
climate_indices-2.2.0.dist-info/METADATA
climate_indices-2.2.0.dist-info/WHEEL
climate_indices-2.2.0.dist-info/entry_points.txt
climate_indices-2.2.0.dist-info/licenses/LICENSE
climate_indices-2.2.0.dist-info/RECORD
