Metadata-Version: 2.4
Name: climate_indices
Version: 2.2.0
Summary: Reference implementations of various climate indices typically used for drought monitoring
Project-URL: Homepage, https://github.com/monocongo/climate_indices
Project-URL: Bug Tracker, https://github.com/monocongo/climate_indices/issues
Author-email: James Adams <monocongo@gmail.com>
License-File: LICENSE
Classifier: Development Status :: 5 - Production/Stable
Classifier: Intended Audience :: Developers
Classifier: Intended Audience :: Education
Classifier: Intended Audience :: Science/Research
Classifier: License :: OSI Approved :: BSD License
Classifier: Programming Language :: Python :: 3.10
Classifier: Programming Language :: Python :: 3.11
Classifier: Programming Language :: Python :: 3.12
Classifier: Programming Language :: Python :: 3.13
Classifier: Topic :: Scientific/Engineering :: Atmospheric Science
Classifier: Topic :: Software Development :: Libraries :: Python Modules
Requires-Python: <3.14,>=3.10
Requires-Dist: cftime>=1.6.4.post1
Requires-Dist: dask>=2025.7.0
Requires-Dist: h5netcdf>=1.6.3
Requires-Dist: scipy>=1.15.3
Requires-Dist: xarray>=2025.6.1
Provides-Extra: dev
Requires-Dist: cartopy>=0.24.1; extra == 'dev'
Requires-Dist: coverage>=7.10.1; extra == 'dev'
Requires-Dist: jupyter>=1.1.1; extra == 'dev'
Requires-Dist: matplotlib>=3.10.3; extra == 'dev'
Requires-Dist: pytest-cov>=6.2.1; extra == 'dev'
Requires-Dist: pytest>=8.4.1; extra == 'dev'
Requires-Dist: ruff>=0.12.7; extra == 'dev'
Requires-Dist: sphinx-autodoc-typehints>=3.0.1; extra == 'dev'
Requires-Dist: toml>=0.10.2; extra == 'dev'
Provides-Extra: docs
Requires-Dist: sphinx-rtd-theme>=1.0; extra == 'docs'
Requires-Dist: sphinx>=8.1.3; extra == 'docs'
